ygor/__init__.py
ygor/__main__.py
ygor/igor.py
ygor-0.5.dist-info/DESCRIPTION.rst
ygor-0.5.dist-info/METADATA
ygor-0.5.dist-info/RECORD
ygor-0.5.dist-info/WHEEL
ygor-0.5.dist-info/entry_points.txt
ygor-0.5.dist-info/metadata.json
ygor-0.5.dist-info/top_level.txt
