Metadata-Version: 2.0
Name: ygor
Version: 0.5
Summary: Minimal experiment runner
Home-page: UNKNOWN
Author: Hannes Ovrén
Author-email: hannes.ovren@liu.se
License: UNKNOWN
Platform: UNKNOWN
